{
    "appid": "${bd_app_id}",
    "name": "${project_name}",
    "libVersion": "1.0.10",
    "libversion": "game",
    "compileType": "game",
    "setting": {
        "urlCheck": false
    },
    "bundle": {
        "exclude": [
            "node_moudules"
        ],
        "entry": "game.js",
        "processors": [
            {
                "type": "babel",
                "exclude": [
                    "lib/*.js"
                ]
            },
            {
                "type": "provideRequire",
                "include": []
            }
        ]
    }
}